idsred/__init__.py
idsred/_version.py
idsred/env.py
idsred/fluxcalib.py
idsred/spec1Dreduc.py
idsred/spec2Dreduc.py
idsred/utils.py
idsred/wavecalib.py
idsred/extinction/lapalmaext.txt
idsred/lamps/CuArNe_high.dat
idsred/lamps/CuArNe_low.dat
idsred/lamps/CuAr_high.dat
idsred/lamps/CuAr_low.dat
idsred/lamps/CuNe_high.dat
idsred/lamps/CuNe_low.dat
idsred/lamps/init_wavesol.txt
idsred/lamps/init_wavesol_no_timming.txt
idsred/standards/bd17.og
idsred/standards/bd253.sto
idsred/standards/bd253a.sto
idsred/standards/bd254.oke
idsred/standards/bd75.oke
idsred/standards/f25.sto
idsred/standards/fFEIGE110.dat
idsred/standards/fGD153.dat
idsred/standards/fGD71.dat
idsred/standards/g191anew.oke
idsred/standards/h102a.sto
idsred/standards/h600.sto
idsred/standards/hd194a.og
idsred/standards/hd849.og
idsred/standards/standards.json
idsred/standards/w1346.oke
idsred-0.1.1.dist-info/METADATA
idsred-0.1.1.dist-info/WHEEL
idsred-0.1.1.dist-info/top_level.txt
idsred-0.1.1.dist-info/RECORD
