Metadata-Version: 2.1
Name: idsred
Version: 0.1.1
Summary: INT-IDS data-reduction pipeline
Home-page: https://github.com/temuller/idsred
Author: Tomás Enrique Müller-Bravo
Author-email: t.e.muller-bravo@ice.csic.es
License: MIT
Classifier: Programming Language :: Python :: 3
Classifier: License :: OSI Approved :: MIT License
Classifier: Operating System :: OS Independent
Requires-Python: >=3.8
Requires-Dist: numpy
Requires-Dist: pandas
Requires-Dist: matplotlib
Requires-Dist: astropy
Requires-Dist: ccdproc
Requires-Dist: specutils
Requires-Dist: python-dotenv
Requires-Dist: scipy
